pypackhelper-0.1.0.dist-info/licenses/LICENSE
pyph/__init__.py
pyph/__main__.py
pyph/cli.py
pyph/init_package.py
pyph/uploader.py
pyph/validator.py
pyph/version_manager.py
pypackhelper-0.1.0.dist-info/METADATA
pypackhelper-0.1.0.dist-info/WHEEL
pypackhelper-0.1.0.dist-info/entry_points.txt
pypackhelper-0.1.0.dist-info/top_level.txt
pypackhelper-0.1.0.dist-info/RECORD
