Metadata-Version: 2.4
Name: pypackhelper
Version: 0.1.0
Summary: A comprehensive tool for Python package management
Home-page: https://github.com/Okymi-X/PyPackHelper
Author: PyPackHelper Team
Author-email: PyPackHelper Team <contact@pypackhelper.dev>
License: MIT
Project-URL: Homepage, https://github.com/Okymi-X/PyPackHelper
Project-URL: Documentation, https://github.com/Okymi-X/PyPackHelper#readme
Project-URL: Repository, https://github.com/Okymi-X/PyPackHelper.git
Project-URL: Bug Tracker, https://github.com/Okymi-X/PyPackHelper/issues
Keywords: python,packaging,pypi,cli,development
Classifier: Development Status :: 4 - Beta
Classifier: Intended Audience :: Developers
Classifier: License :: OSI Approved :: MIT License
Classifier: Operating System :: OS Independent
Classifier: Programming Language :: Python :: 3
Classifier: Programming Language :: Python :: 3.8
Classifier: Programming Language :: Python :: 3.9
Classifier: Programming Language :: Python :: 3.10
Classifier: Programming Language :: Python :: 3.11
Classifier: Programming Language :: Python :: 3.12
Classifier: Topic :: Software Development :: Libraries :: Python Modules
Classifier: Topic :: Software Development :: Build Tools
Classifier: Topic :: System :: Software Distribution
Requires-Python: >=3.8
License-File: LICENSE
Requires-Dist: typer>=0.9.0
Requires-Dist: python-dotenv>=1.0.0
Requires-Dist: toml>=0.10.2
Provides-Extra: dev
Requires-Dist: pytest>=6.0; extra == "dev"
Requires-Dist: pytest-cov>=2.0; extra == "dev"
Requires-Dist: flake8>=3.8; extra == "dev"
Requires-Dist: black>=21.0; extra == "dev"
Requires-Dist: isort>=5.0; extra == "dev"
Requires-Dist: mypy>=0.800; extra == "dev"
Requires-Dist: build>=0.10.0; extra == "dev"
Requires-Dist: twine>=4.0.0; extra == "dev"
Provides-Extra: full
Requires-Dist: build>=0.10.0; extra == "full"
Requires-Dist: twine>=4.0.0; extra == "full"
Requires-Dist: flake8>=3.8; extra == "full"
Requires-Dist: black>=21.0; extra == "full"
Requires-Dist: isort>=5.0; extra == "full"
Requires-Dist: mypy>=0.800; extra == "full"
Requires-Dist: pytest>=6.0; extra == "full"
Requires-Dist: pytest-cov>=2.0; extra == "full"
Dynamic: author
Dynamic: home-page
Dynamic: license-file
Dynamic: requires-python
